setup.py
pathfinder/chronicle/__init__.py
pathfinder/chronicle/cells.py
pathfinder/chronicle/generate_sheets.py
pathfinder/chronicle/pdf.py
pathfinder/mapmaker/__init__.py
pathfinder/mapmaker/build_maps.py
pathfinder/mapmaker/extract.py
pathfinder/mapmaker/grid.py
pathfinder/mapmaker/waifu2x_pytorch.py
pathfinder/mapmaker/pytorch/CARN_model_checkpoint.pt
pathfinder/mapmaker/pytorch/__init__.py
pathfinder/pfsweb/__init__.py
pathfinder/pfsweb/config.py
pathfinder/pfsweb/forms.py
pathfinder/pfsweb/routes.py
pathfinder/pydice/__init__.py
pathfinder/pydice/pathfinder.py
pathfinder/pyfeats/__init__.py
pathfinder/sessions/__init__.py
pathfinder/spells/__init__.py
pathfinder/utils/__init__.py
pathfinder/utils/default_config.yaml
python_pathfinder_tools.egg-info/PKG-INFO
python_pathfinder_tools.egg-info/SOURCES.txt
python_pathfinder_tools.egg-info/dependency_links.txt
python_pathfinder_tools.egg-info/entry_points.txt
python_pathfinder_tools.egg-info/not-zip-safe
python_pathfinder_tools.egg-info/requires.txt
python_pathfinder_tools.egg-info/top_level.txt