Metadata-Version: 1.1
Name: python-pathfinder-tools
Version: 0.4.2
Summary: Python code to do various helpful pathfinder RPG related things
Home-page: https://github.com/tomoinn/python-pathfinder-tools/
Author: Tom Oinn
Author-email: tomoinn@gmail.com
License: GPL3
Platform: UNKNOWN
Classifier: Programming Language :: Python :: 3.8
